AUTHORS.rst
CONTRIBUTING.rst
HISTORY.rst
LICENSE
MANIFEST.in
README.rst
setup.cfg
setup.py
docs/Makefile
docs/authors.rst
docs/conf.py
docs/contributing.rst
docs/history.rst
docs/index.rst
docs/installation.rst
docs/make.bat
docs/readme.rst
docs/usage.rst
sclust/__init__.py
sclust/sclust.py
sclust/sclust_summarize.py
sclust.egg-info/PKG-INFO
sclust.egg-info/SOURCES.txt
sclust.egg-info/dependency_links.txt
sclust.egg-info/entry_points.txt
sclust.egg-info/not-zip-safe
sclust.egg-info/requires.txt
sclust.egg-info/top_level.txt
tests/__init__.py
tests/test_sclust.py