Metadata-Version: 1.1
Name: sclust
Version: 0.1.0
Summary: simple sentence clusterer
Home-page: https://github.com/aronwc/sclust
Author: Aron Culotta
Author-email: aronwc@gmail.com
License: ISCL
Keywords: sclust
Platform: UNKNOWN
Classifier: Development Status :: 2 - Pre-Alpha
Classifier: Intended Audience :: Developers
Classifier: License :: OSI Approved :: ISC License (ISCL)
Classifier: Natural Language :: English
Classifier: Programming Language :: Python :: 2
Classifier: Programming Language :: Python :: 2.7
Classifier: Programming Language :: Python :: 3
Classifier: Programming Language :: Python :: 3.3
Classifier: Programming Language :: Python :: 3.4
Classifier: Programming Language :: Python :: 3.5
